pyauthorizer/__init__.py
pyauthorizer/__main__.py
pyauthorizer/_version.py
pyauthorizer/_version.pyi
pyauthorizer/cli.py
pyauthorizer/exceptions.py
pyauthorizer/py.typed
pyauthorizer/encryptor/__init__.py
pyauthorizer/encryptor/base.py
pyauthorizer/encryptor/interface.py
pyauthorizer/encryptor/plugin_manager.py
pyauthorizer/encryptor/utils.py
pyauthorizer/encryptor/builtin/__init__.py
pyauthorizer/encryptor/builtin/multiple.py
pyauthorizer/encryptor/builtin/simple.py
pyauthorizer-0.2.15.dist-info/LICENSE
pyauthorizer-0.2.15.dist-info/METADATA
pyauthorizer-0.2.15.dist-info/WHEEL
pyauthorizer-0.2.15.dist-info/entry_points.txt
pyauthorizer-0.2.15.dist-info/top_level.txt
pyauthorizer-0.2.15.dist-info/RECORD
