Metadata-Version: 2.1
Name: pyauthorizer
Version: 0.2.15
Summary: A simple authorizer for python project.
Author-email: msclock <msclock@126.com>
License: Apache 2.0
Project-URL: Homepage, https://github.com/msclock/pyauthorizer
Project-URL: Tracker, https://github.com/msclock/pyauthorizer/issues
Project-URL: Documentation, https://github.com/msclock/pyauthorizer.git
Project-URL: Source, https://github.com/msclock/pyauthorizer.git
Project-URL: Changelog, https://github.com/msclock/pyauthorizer/releases
Keywords: license,license-generator
Classifier: Development Status :: 4 - Beta
Classifier: License :: OSI Approved :: Apache Software License
Classifier: Operating System :: OS Independent
Classifier: Intended Audience :: Developers
Classifier: Intended Audience :: Science/Research
Classifier: Programming Language :: Python :: 3
Classifier: Programming Language :: Python :: 3 :: Only
Classifier: Programming Language :: Python :: 3.8
Classifier: Programming Language :: Python :: 3.9
Classifier: Programming Language :: Python :: 3.10
Classifier: Programming Language :: Python :: 3.11
Classifier: Topic :: Software Development :: Libraries
Classifier: Topic :: Software Development :: Libraries :: Python Modules
Classifier: Topic :: Education
Classifier: Topic :: Scientific/Engineering
Classifier: Typing :: Typed
Requires-Python: >=3.8
License-File: LICENSE
Requires-Dist: loguru
Requires-Dist: click
Requires-Dist: cryptography >=41.0.0
Requires-Dist: entrypoints
Requires-Dist: types-entrypoints
Provides-Extra: dev
Requires-Dist: pyauthorizer[docs,test] ; extra == 'dev'
Requires-Dist: build ; extra == 'dev'
Requires-Dist: wheel ; extra == 'dev'
Provides-Extra: docs
Requires-Dist: sphinx >=7.0 ; extra == 'docs'
Requires-Dist: furo >=2023.08.17 ; extra == 'docs'
Requires-Dist: myst-parser >=0.13 ; extra == 'docs'
Requires-Dist: sphinx-copybutton ; extra == 'docs'
Requires-Dist: sphinx-autodoc-typehints ; extra == 'docs'
Requires-Dist: sphinx-inline-tabs ; extra == 'docs'
Provides-Extra: test
Requires-Dist: pytest >=6 ; extra == 'test'
Requires-Dist: pytest-cov >=3 ; extra == 'test'
